emdfile/__init__.py
emdfile/read.py
emdfile/read_EMD_v0p1.py
emdfile/tqdmnd.py
emdfile/utils.py
emdfile/version.py
emdfile/write.py
emdfile/classes/__init__.py
emdfile/classes/array.py
emdfile/classes/custom.py
emdfile/classes/metadata.py
emdfile/classes/node.py
emdfile/classes/pointlist.py
emdfile/classes/pointlistarray.py
emdfile/classes/root.py
emdfile/classes/utils.py
emdfile-0.0.16.dist-info/METADATA
emdfile-0.0.16.dist-info/WHEEL
emdfile-0.0.16.dist-info/licenses/LICENSE
emdfile-0.0.16.dist-info/RECORD
