Metadata-Version: 2.3
Name: emdfile
Version: 0.0.16
Project-URL: github, https://github.com/py4dstem/emdfile
Project-URL: emdatasets, https://emdatasets.com/format/
Author-email: "Benjamin H. Savitzky" <ben.savitzky@gmail.com>
License: MIT License
License-File: LICENSE
Classifier: License :: OSI Approved :: MIT License
Classifier: Programming Language :: Python :: 3
Requires-Python: >=3.8
Requires-Dist: h5py>=3.2.0
Requires-Dist: numpy
Requires-Dist: tqdm>=4.46.1
Provides-Extra: docs
Requires-Dist: sphinx==8.0.2; extra == 'docs'
